biobb_morph/__init__.py
biobb_morph/py.typed
biobb_morph/morph/__init__.py
biobb_morph/morph/common.py
biobb_morph/morph/createTZ.py
biobb_morph/morph/failedElem.py
biobb_morph/morph/morph.py
biobb_morph/morph/morphFunctions.py
biobb_morph/sources/lambdaBeta.csv
biobb_morph/sources/functions/createTZ.py
biobb_morph/sources/functions/failedElem.py
biobb_morph/sources/functions/morphFunctions.py
biobb_morph/sources/functions/morphFunctions.py.bkp
biobb_morph/sources/template/L4-L5_complete.inp
biobb_morph/sources/template/L4-L5_noBEP.txt
biobb_morph/sources/template/L4-L5_noBEP_noIndex.txt
biobb_morph/sources/template/L4-L5_shell.inp
biobb_morph/sources/template/L4-L5_shell_coords.txt
biobb_morph/sources/template/correspondingNodesFebAbqs.txt
biobb_morph/sources/template/obtainCoordFromNodes.py
biobb_morph/sources/template/templateCEPlower.inp
biobb_morph/sources/template/templateCEPlower.txt
biobb_morph/sources/template/templateCEPlower_down.txt
biobb_morph/sources/template/templateCEPlower_up.txt
biobb_morph/sources/template/templateCEPupper.inp
biobb_morph/sources/template/templateCEPupper.txt
biobb_morph/sources/template/templateCEPupper_down.txt
biobb_morph/sources/template/templateCEPupper_up.txt
biobb_morph/sources/template/template_AF.inp
biobb_morph/sources/template/template_AF.txt
biobb_morph/sources/template/template_AF_WCEP.inp
biobb_morph/sources/template/template_AF_WCEP.txt
biobb_morph/sources/template/template_L4-L5.msh
biobb_morph/sources/template/template_L4-L5_noBEP.inp
biobb_morph/sources/template/template_NP.inp
biobb_morph/sources/template/template_NP.txt
biobb_morph/sources/template/template_NP_WCEP.inp
biobb_morph/sources/template/template_NP_WCEP.txt
biobb_morph/sources/template/components/annulus.inp
biobb_morph/sources/template/components/collagen.inp
biobb_morph/sources/template/components/controls.inp
biobb_morph/sources/template/components/emme.inp
biobb_morph/sources/template/components/endplate.inp
biobb_morph-5.0.1.dist-info/LICENSE
biobb_morph-5.0.1.dist-info/METADATA
biobb_morph-5.0.1.dist-info/WHEEL
biobb_morph-5.0.1.dist-info/entry_points.txt
biobb_morph-5.0.1.dist-info/top_level.txt
biobb_morph-5.0.1.dist-info/RECORD
