Metadata-Version: 2.1
Name: biobb_morph
Version: 5.0.1
Summary: biobb_morph is the Biobb module collection to create patien-specific 3D meshes from IVD template examples.
Home-page: https://github.com/bioexcel/biobb_morph
Author: Biobb developers
Author-email: mferri@bsc.es
Project-URL: Documentation, http://biobb-morph.readthedocs.io/en/latest/
Project-URL: Bioexcel, https://bioexcel.eu/
Keywords: Bioinformatics Workflows BioExcel Compatibility
Classifier: Development Status :: 5 - Production/Stable
Classifier: Programming Language :: Python :: 3.9
Classifier: License :: OSI Approved :: Apache Software License
Classifier: Operating System :: MacOS :: MacOS X
Classifier: Operating System :: POSIX
Classifier: Operating System :: Unix
Requires-Python: >=3.9
License-File: LICENSE
Requires-Dist: biobb-common==5.0.0
Requires-Dist: torch
Requires-Dist: numpy-stl
Requires-Dist: numpy
Requires-Dist: trimesh
Requires-Dist: matplotlib
Requires-Dist: scikit-learn
Requires-Dist: scipy
Requires-Dist: meshio
Requires-Dist: Rtree
